site_to_markdown/__init__.py
site_to_markdown/run.py
site_to_markdown/spider.py
site_to_markdown-0.2.0.dist-info/METADATA
site_to_markdown-0.2.0.dist-info/WHEEL
site_to_markdown-0.2.0.dist-info/entry_points.txt
site_to_markdown-0.2.0.dist-info/licenses/LICENSE
site_to_markdown-0.2.0.dist-info/RECORD
