Metadata-Version: 2.3
Name: site_to_markdown
Version: 0.2.0
Summary: A tool to scrape a website and convert it to markdown.
Project-URL: Homepage, https://github.com/andrewgross/site_to_markdown
Project-URL: Issues, https://github.com/andrewgross/site_to_markdown/issues
Author: Andrew Gross
Classifier: License :: OSI Approved :: MIT License
Classifier: Operating System :: OS Independent
Classifier: Programming Language :: Python :: 3
Requires-Python: >=3.12
Requires-Dist: langdetect
Requires-Dist: lxml[html-clean]
Requires-Dist: markdownify
Requires-Dist: readability-lxml
Requires-Dist: scrapy
